Workbook

Sheet Parameters
A1: Parameter | B1: Value | C1: Notes
A2: Win payment ($/share) | B2: 5 | C2: SDMM-1 game settlement accrual: win
A3: Tie payment ($/share) | B3: 2.5 | C3: SDMM-1 game settlement accrual: tie (NFL only)
A4: Off-field pool ($/game) | B4: 2.5 | C4: Split pro rata by counted share volume (Spec v1.1); full pool vs non-universe opponent (Spec v1.2)
A5: Sigma — NFL season wins | B5: 2.7 | C5: SD of 17-game win distribution around the market total
A6: Sigma — NCAA season wins | B6: 2.2 | C6: SD of 12-game win distribution around the market total
A7: Expected NFL ties/team | B7: 0.08 | C7: ~1-2 ties league-wide per season
A8: NFL games | B8: 17 | C8: Regular season only (Spec v1.2)
A9: NCAA games | B9: 12 | C9: Regular season only (Spec v1.2)
A10: IPO price tick ($) | B10: 0.01 | C10: Rounding increment for listed IPO price — penny tick per IPO mechanics decision
A11: Capture clamp low | B11: 0.2 | C11: Per-game volume capture floor (Popularity Index spec)
A12: Capture clamp high | B12: 0.8 | C12: Per-game volume capture ceiling
A13: Brand weight (popularity) | B13: 0.6 | C13: Pop = 0.6*Brand + 0.4*PerfIndex — engine.py input
... A18: No-discount guaranteed threshold | B18: 0.2 | C18: Names whose guaranteed accrual (OOU games x pool) exceeds this share of EV list at full EV — no discount on near-riskless value (catches North Dakota State and Sacramento State)
A20: Legend: yellow/blue cells are tunable inputs. Rows 2-12 and 16-18 flow live into the NFL IPO / NCAA IPO formulas. Rows 13-15 are engine.py inputs — changing them requires rerunning engine.py to refresh Brand/Popularity/Avg Capture columns.
A21: Example: set B2 to 6.00 or the discount band in B16:B17 and both IPO tabs reprice instantly.

Sheet NFL IPO
A1: Team | B1: Conf/Div | C1: Win Total | D1: Over | E1: Under | F1: Imp P(Over) | G1: Imp P(Under) | H1: P(Over) devig | I1: E[Wins] | J1: Brand | K1: Popularity | L1: Avg Capture | M1: OOU Games | N1: On-Field EV | O1: Off-Field EV | P1: IPO EV | Q1: Contested Off-Field % | R1: Discount | S1: Listed IPO
A2: Los Angeles Rams | B2: NFC West | C2: 11.5 | D2: -140 | E2: 115 | F2: =IF(D2>0,100/(D2+100),-D2/(-D2+100)) -> 0.58333333 | G2: =IF(E2>0,100/(E2+100),-E2/(-E2+100)) -> 0.46511628 | H2: =F2/(F2+G2) -> 0.55637708 | I2: =C2+Parameters!$B$5*NORMSINV(H2) -> 11.882833 | J2: 68 | K2: 68.76 | L2: 0.5272 | M2: 0 | N2: =Parameters!$B$2*I2+Parameters!$B$3*Parameters!$B$7 -> 59.614166 | O2: =Parameters!$B$4*Parameters!$B$8*L2 -> 22.406 | P2: =N2+O2 -> 82.020166 | Q2: =(O2-Parameters!$B$4*M2)/P2 -> 0.27317672 | R2: =IF(Parameters!$B$4*M2/P2>Parameters!$B$18,0,Parameters!$B$16+(Parameters!$B$17-Parameters!$B$16)*(Q2-MIN(Q$2:Q$33))/(MAX(Q$2:Q$33)-MIN(Q$2:Q$33))) -> 0.01 | S2: =ROUND(P2*(1-R2)/Parameters!$B$10,0)*Parameters!$B$10 -> 81.2
A3: Baltimore Ravens | B3: AFC North | C3: 11.5 | D3: 118 | E3: -140 | F3: =IF(D3>0,100/(D3+100),-D3/(-D3+100)) -> 0.4587156 | G3: =IF(E3>0,100/(E3+100),-E3/(-E3+100)) -> 0.58333333 | H3: =F3/(F3+G3) -> 0.44020543 | I3: =C3+Parameters!$B$5*NORMSINV(H3) -> 11.093789 | J3: 76 | K3: 71.7 | L3: 0.5341 | M3: 0 | N3: =Parameters!$B$2*I3+Parameters!$B$3*Parameters!$B$7 -> 55.668947 | O3: =Parameters!$B$4*Parameters!$B$8*L3 -> 22.69925 | P3: =N3+O3 -> 78.368197 | Q3: =(O3-Parameters!$B$4*M3)/P3 -> 0.28964875 | R3: =IF(Parameters!$B$4*M3/P3>Parameters!$B$18,0,Parameters!$B$16+(Parameters!$B$17-Parameters!$B$16)*(Q3-MIN(Q$2:Q$33))/(MAX(Q$2:Q$33)-MIN(Q$2:Q$33))) -> 0.01157246 | S3: =ROUND(P3*(1-R3)/Parameters!$B$10,0)*Parameters!$B$10 -> 77.46
A4: Buffalo Bills | B4: AFC East | C4: 10.5 | D4: -145 | E4: 120 | F4: =IF(D4>0,100/(D4+100),-D4/(-D4+100)) -> 0.59183673 | G4: =IF(E4>0,100/(E4+100),-E4/(-E4+100)) -> 0.45454545 | H4: =F4/(F4+G4) -> 0.56560284 | I4: =C4+Parameters!$B$5*NORMSINV(H4) -> 10.946013 | J4: 80 | K4: 73.76 | L4: 0.5485 | M4: 0 | N4: =Parameters!$B$2*I4+Parameters!$B$3*Parameters!$B$7 -> 54.930067 | O4: =Parameters!$B$4*Parameters!$B$8*L4 -> 23.31125 | P4: =N4+O4 -> 78.241317 | Q4: =(O4-Parameters!$B$4*M4)/P4 -> 0.29794041 | R4: =IF(Parameters!$B$4*M4/P4>Parameters!$B$18,0,Parameters!$B$16+(Parameters!$B$17-Parameters!$B$16)*(Q4-MIN(Q$2:Q$33))/(MAX(Q$2:Q$33)-MIN(Q$2:Q$33))) -> 0.012364002 | S4: =ROUND(P4*(1-R4)/Parameters!$B$10,0)*Parameters!$B$10 -> 77.27
A5: Detroit Lions | B5: NFC North | C5: 10.5 | D5: -130 | E5: 110 | F5: =IF(D5>0,100/(D5+100),-D5/(-D5+100)) -> 0.56521739 | G5: =IF(E5>0,100/(E5+100),-E5/(-E5+100)) -> 0.47619048 | H5: =F5/(F5+G5) -> 0.54274354 | I5: =C5+Parameters!$B$5*NORMSINV(H5) -> 10.78984 | J5: 82 | K5: 74.59 | L5: 0.5389 | M5: 0 | N5: =Parameters!$B$2*I5+Parameters!$B$3*Parameters!$B$7 -> 54.149198 | O5: =Parameters!$B$4*Parameters!$B$8*L5 -> 22.90325 | P5: =N5+O5 -> 77.052448 | Q5: =(O5-Parameters!$B$4*M5)/P5 -> 0.29724234 | R5: =IF(Parameters!$B$4*M5/P5>Parameters!$B$18,0,Parameters!$B$16+(Parameters!$B$17-Parameters!$B$16)*(Q5-MIN(Q$2:Q$33))/(MAX(Q$2:Q$33)-MIN(Q$2:Q$33))) -> 0.012297363 | S5: =ROUND(P5*(1-R5)/Parameters!$B$10,0)*Parameters!$B$10 -> 76.1
A6: Seattle Seahawks | B6: NFC West | C6: 10.5 | D6: -125 | E6: 105 | F6: =IF(D6>0,100/(D6+100),-D6/(-D6+100)) -> 0.55555556 | G6: =IF(E6>0,100/(E6+100),-E6/(-E6+100)) -> 0.48780488 | H6: =F6/(F6+G6) -> 0.53246753 | I6: =C6+Parameters!$B$5*NORMSINV(H6) -> 10.71998 | J6: 70 | K6: 67.22 | L6: 0.5209 | M6: 0 | N6: =Parameters!$B$2*I6+Parameters!$B$3*Parameters!$B$7 -> 53.7999 | O6: =Parameters!$B$4*Parameters!$B$8*L6 -> 22.13825 | P6: =N6+O6 -> 75.93815 | Q6: =(O6-Parameters!$B$4*M6)/P6 -> 0.29153001 | R6: =IF(Parameters!$B$4*M6/P6>Parameters!$B$18,0,Parameters!$B$16+(Parameters!$B$17-Parameters!$B$16)*(Q6-MIN(Q$2:Q$33))/(MAX(Q$2:Q$33)-MIN(Q$2:Q$33))) -> 0.01175205 | S6: =ROUND(P6*(1-R6)/Parameters!$B$10,0)*Parameters!$B$10 -> 75.05
A7: San Francisco 49ers | B7: NFC West | C7: 10.5 | D7: 105 | E7: -125 | F7: =IF(D7>0,100/(D7+100),-D7/(-D7+100)) -> 0.48780488 | G7: =IF(E7>0,100/(E7+100),-E7/(-E7+100)) -> 0.55555556 | H7: =F7/(F7+G7) -> 0.46753247 | I7: =C7+Parameters!$B$5*NORMSINV(H7) -> 10.28002 | J7: 88 | K7: 76.99 | L7: 0.5583 | M7: 0 | N7: =Parameters!$B$2*I7+Parameters!$B$3*Parameters!$B$7 -> 51.6001 | O7: =Parameters!$B$4*Parameters!$B$8*L7 -> 23.72775 | P7: =N7+O7 -> 75.32785 | Q7: =(O7-Parameters!$B$4*M7)/P7 -> 0.31499306 | R7: =IF(Parameters!$B$4*M7/P7>Parameters!$B$18,0,Parameters!$B$16+(Parameters!$B$17-Parameters!$B$16)*(Q7-MIN(Q$2:Q$33))/(MAX(Q$2:Q$33)-MIN(Q$2:Q$33))) -> 0.01399189 | S7: =ROUND(P7*(1-R7)/Parameters!$B$10,0)*Parameters!$B$10 -> 74.27
A8: Kansas City Chiefs | B8: AFC West | C8: 10.5 | D8: 115 | E8: -135 | F8: =IF(D8>0,100/(D8+100),-D8/(-D8+100)) -> 0.46511628 | G8: =IF(E8>0,100/(E8+100),-E8/(-E8+100)) -> 0.57446809 | H8: =F8/(F8+G8) -> 0.447406 | I8: =C8+Parameters!$B$5*NORMSINV(H8) -> 10.143012 | J8: 95 | K8: 80.87 | L8: 0.5677 | M8: 0 | N8: =Parameters!$B$2*I8+Parameters!$B$3*Parameters!$B$7 -> 50.915059 | O8: =Parameters!$B$4*Parameters!$B$8*L8 -> 24.12725 | P8: =N8+O8 -> 75.042309 | Q8: =(O8-Parameters!$B$4*M8)/P8 -> 0.32151529 | R8: =IF(Parameters!$B$4*M8/P8>Parameters!$B$18,0,Parameters!$B$16+(Parameters!$B$17-Parameters!$B$16)*(Q8-MIN(Q$2:Q$33))/(MAX(Q$2:Q$33)-MIN(Q$2:Q$33))) -> 0.014614518 | S8: =ROUND(P8*(1-R8)/Parameters!$B$10,0)*Parameters!$B$10 -> 73.95
A9: Philadelphia Eagles | B9: NFC East | C9: 10.5 | D9: 120 | E9: -145 | F9: =IF(D9>0,100/(D9+100),-D9/(-D9+100)) -> 0.45454545 | G9: =IF(E9>0,100/(E9+100),-E9/(-E9+100)) -> 0.59183673 | H9: =F9/(F9+G9) -> 0.43439716 | I9: =C9+Parameters!$B$5*NORMSINV(H9) -> 10.053987 | J9: 90 | K9: 77.66 | L9: 0.552 | M9: 0 | N9: =Parameters!$B$2*I9+Parameters!$B$3*Parameters!$B$7 -> 50.469933 | O9: =Parameters!$B$4*Parameters!$B$8*L9 -> 23.46 | P9: =N9+O9 -> 73.929933 | Q9: =(O9-Parameters!$B$4*M9)/P9 -> 0.31732749 | R9: =IF(Parameters!$B$4*M9/P9>Parameters!$B$18,0,Parameters!$B$16+(Parameters!$B$17-Parameters!$B$16)*(Q9-MIN(Q$2:Q$33))/(MAX(Q$2:Q$33)-MIN(Q$2:Q$33))) -> 0.01421474 | S9: =ROUND(P9*(1-R9)/Parameters!$B$10,0)*Parameters!$B$10 -> 72.88
A10: New England Patriots | B10: AFC East | C10: 10.5 | D10: 120 | E10: -145 | F10: =IF(D10>0,100/(D10+100),-D10/(-D10+100)) -> 0.45454545 | G10: =IF(E10>0,100/(E10+100),-E10/(-E10+100)) -> 0.59183673 | H10: =F10/(F10+G10) -> 0.43439716 | I10: =C10+Parameters!$B$5*NORMSINV(H10) -> 10.053987 | J10: 78 | K10: 70.46 | L10: 0.5359 | M10: 0 | N10: =Parameters!$B$2*I10+Parameters!$B$3*Parameters!$B$7 -> 50.469933 | O10: =Parameters!$B$4*Parameters!$B$8*L10 -> 22.77575 | P10: =N10+O10 -> 73.245683 | Q10: =(O10-Parameters!$B$4*M10)/P10 -> 0.31095007 | R10: =IF(Parameters!$B$4*M10/P10>Parameters!$B$18,0,Parameters!$B$16+(Parameters!$B$17-Parameters!$B$16)*(Q10-MIN(Q$2:Q$33))/(MAX(Q$2:Q$33)-MIN(Q$2:Q$33))) -> 0.013605936 | S10: =ROUND(P10*(1-R10)/Parameters!$B$10,0)*Parameters!$B$10 -> 72.25
A11: Cincinnati Bengals | B11: AFC North | C11: 10.5 | D11: 115 | E11: -140 | F11: =IF(D11>0,100/(D11+100),-D11/(-D11+100)) -> 0.46511628 | G11: =IF(E11>0,100/(E11+100),-E11/(-E11+100)) -> 0.58333333 | H11: =F11/(F11+G11) -> 0.44362292 | I11: =C11+Parameters!$B$5*NORMSINV(H11) -> 10.117167 | J11: 72 | K11: 67.01 | L11: 0.5153 | M11: 0 | N11: =Parameters!$B$2*I11+Parameters!$B$3*Parameters!$B$7 -> 50.785834 | O11: =Parameters!$B$4*Parameters!$B$8*L11 -> 21.90025 | P11: =N11+O11 -> 72.686084 | Q11: =(O11-Parameters!$B$4*M11)/P11 -> 0.30129908 | R11: =IF(Parameters!$B$4*M11/P11>Parameters!$B$18,0,Parameters!$B$16+(Parameters!$B$17-Parameters!$B$16)*(Q11-MIN(Q$2:Q$33))/(MAX(Q$2:Q$33)-MIN(Q$2:Q$33))) -> 0.012684629 | S11: =ROUND(P11*(1-R11)/Parameters!$B$10,0)*Parameters!$B$10 -> 71.76
A12: Green Bay Packers | B12: NFC North | C12: 9.5 | D12: -125 | E12: 105 | F12: =IF(D12>0,100/(D12+100),-D12/(-D12+100)) -> 0.55555556 | G12: =IF(E12>0,100/(E12+100),-E12/(-E12+100)) -> 0.48780488 | H12: =F12/(F12+G12) -> 0.53246753 | I12: =C12+Parameters!$B$5*NORMSINV(H12) -> 9.71998 | J12: 88 | K12: 75.67 | L12: 0.5429 | M12: 0 | N12: =Parameters!$B$2*I12+Parameters!$B$3*Parameters!$B$7 -> 48.7999 | O12: =Parameters!$B$4*Parameters!$B$8*L12 -> 23.07325 | P12: =N12+O12 -> 71.87315 | Q12: =(O12-Parameters!$B$4*M12)/P12 -> 0.32102739 | R12: =IF(Parameters!$B$4*M12/P12>Parameters!$B$18,0,Parameters!$B$16+(Parameters!$B$17-Parameters!$B$16)*(Q12-MIN(Q$2:Q$33))/(MAX(Q$2:Q$33)-MIN(Q$2:Q$33))) -> 0.014567942 | S12: =ROUND(P12*(1-R12)/Parameters!$B$10,0)*Parameters!$B$10 -> 70.83
A13: Dallas Cowboys | B13: NFC East | C13: 9.5 | D13: 105 | E13: -125 | F13: =IF(D13>0,100/(D13+100),-D13/(-D13+100)) -> 0.48780488 | G13: =IF(E13>0,100/(E13+100),-E13/(-E13+100)) -> 0.55555556 | H13: =F13/(F13+G13) -> 0.46753247 | I13: =C13+Parameters!$B$5*NORMSINV(H13) -> 9.28002 | J13: 100 | K13: 81.84 | L13: 0.5664 | M13: 0 | N13: =Parameters!$B$2*I13+Parameters!$B$3*Parameters!$B$7 -> 46.6001 | O13: =Parameters!$B$4*Parameters!$B$8*L13 -> 24.072 | P13: =N13+O13 -> 70.6721 | Q13: =(O13-Parameters!$B$4*M13)/P13 -> 0.34061532 | R13: =IF(Parameters!$B$4*M13/P13>Parameters!$B$18,0,Parameters!$B$16+(Parameters!$B$17-Parameters!$B$16)*(Q13-MIN(Q$2:Q$33))/(MAX(Q$2:Q$33)-MIN(Q$2:Q$33))) -> 0.016437854 | S13: =ROUND(P13*(1-R13)/Parameters!$B$10,0)*Parameters!$B$10 -> 69.51
... A33: Arizona Cardinals | B33: NFC West | C33: 3.5 | D33: -145 | E33: 120 | F33: =IF(D33>0,100/(D33+100),-D33/(-D33+100)) -> 0.59183673 | G33: =IF(E33>0,100/(E33+100),-E33/(-E33+100)) -> 0.45454545 | H33: =F33/(F33+G33) -> 0.56560284 | I33: =C33+Parameters!$B$5*NORMSINV(H33) -> 3.9460134 | J33: 55 | K33: 42.28 | L33: 0.3939 | M33: 0 | N33: =Parameters!$B$2*I33+Parameters!$B$3*Parameters!$B$7 -> 19.930067 | O33: =Parameters!$B$4*Parameters!$B$8*L33 -> 16.74075 | P33: =N33+O33 -> 36.670817 | Q33: =(O33-Parameters!$B$4*M33)/P33 -> 0.45651424 | R33: =IF(Parameters!$B$4*M33/P33>Parameters!$B$18,0,Parameters!$B$16+(Parameters!$B$17-Parameters!$B$16)*(Q33-MIN(Q$2:Q$33))/(MAX(Q$2:Q$33)-MIN(Q$2:Q$33))) -> 0.027501848 | S33: =ROUND(P33*(1-R33)/Parameters!$B$10,0)*Parameters!$B$10 -> 35.66
A35: Blue cells = inputs (odds, brand/popularity/capture from engine.py). Black = live formulas driven by the Parameters tab.

Sheet NCAA IPO
A1: Team | B1: Conf/Div | C1: Win Total | D1: Over | E1: Under | F1: Imp P(Over) | G1: Imp P(Under) | H1: P(Over) devig | I1: E[Wins] | J1: Brand | K1: Popularity | L1: Avg Capture | M1: OOU Games | N1: On-Field EV | O1: Off-Field EV | P1: IPO EV | Q1: Contested Off-Field % | R1: Discount | S1: Listed IPO
A2: Texas Tech | B2: Big 12 | C2: 10.5 | D2: -220 | E2: 170 | F2: =IF(D2>0,100/(D2+100),-D2/(-D2+100)) -> 0.6875 | G2: =IF(E2>0,100/(E2+100),-E2/(-E2+100)) -> 0.37037037 | H2: =F2/(F2+G2) -> 0.64989059 | I2: =C2+Parameters!$B$6*NORMSINV(H2) -> 11.347055 | J2: 56 | K2: 71.42 | L2: 0.5945 | M2: 1 | N2: =Parameters!$B$2*I2 -> 56.735276 | O2: =Parameters!$B$4*((Parameters!$B$9-M2)*L2+M2) -> 18.84875 | P2: =N2+O2 -> 75.584026 | Q2: =(O2-Parameters!$B$4*M2)/P2 -> 0.21629901 | R2: =IF(Parameters!$B$4*M2/P2>Parameters!$B$18,0,Parameters!$B$16+(Parameters!$B$17-Parameters!$B$16)*(Q2-MIN(Q$2:Q$139))/(MAX(Q$2:Q$139)-MIN(Q$2:Q$139))) -> 0.019662104 | S2: =ROUND(P2*(1-R2)/Parameters!$B$10,0)*Parameters!$B$10 -> 74.1
A3: Notre Dame | B3: Independent | C3: 11.5 | D3: 150 | E3: -200 | F3: =IF(D3>0,100/(D3+100),-D3/(-D3+100)) -> 0.4 | G3: =IF(E3>0,100/(E3+100),-E3/(-E3+100)) -> 0.66666667 | H3: =F3/(F3+G3) -> 0.375 | I3: =C3+Parameters!$B$6*NORMSINV(H3) -> 10.798993 | J3: 94 | K3: 92.4 | L3: 0.6817 | M3: 0 | N3: =Parameters!$B$2*I3 -> 53.994967 | O3: =Parameters!$B$4*((Parameters!$B$9-M3)*L3+M3) -> 20.451 | P3: =N3+O3 -> 74.445967 | Q3: =(O3-Parameters!$B$4*M3)/P3 -> 0.27470931 | R3: =IF(Parameters!$B$4*M3/P3>Parameters!$B$18,0,Parameters!$B$16+(Parameters!$B$17-Parameters!$B$16)*(Q3-MIN(Q$2:Q$139))/(MAX(Q$2:Q$139)-MIN(Q$2:Q$139))) -> 0.02281312 | S3: =ROUND(P3*(1-R3)/Parameters!$B$10,0)*Parameters!$B$10 -> 72.75
A4: Miami Florida | B4: ACC | C4: 10.5 | D4: -125 | E4: 100 | F4: =IF(D4>0,100/(D4+100),-D4/(-D4+100)) -> 0.55555556 | G4: =IF(E4>0,100/(E4+100),-E4/(-E4+100)) -> 0.5 | H4: =F4/(F4+G4) -> 0.52631579 | I4: =C4+Parameters!$B$6*NORMSINV(H4) -> 10.645226 | J4: 74 | K4: 79.88 | L4: 0.6314 | M4: 1 | N4: =Parameters!$B$2*I4 -> 53.22613 | O4: =Parameters!$B$4*((Parameters!$B$9-M4)*L4+M4) -> 19.8635 | P4: =N4+O4 -> 73.08963 | Q4: =(O4-Parameters!$B$4*M4)/P4 -> 0.23756448 | R4: =IF(Parameters!$B$4*M4/P4>Parameters!$B$18,0,Parameters!$B$16+(Parameters!$B$17-Parameters!$B$16)*(Q4-MIN(Q$2:Q$139))/(MAX(Q$2:Q$139)-MIN(Q$2:Q$139))) -> 0.020809296 | S4: =ROUND(P4*(1-R4)/Parameters!$B$10,0)*Parameters!$B$10 -> 71.57
A5: North Dakota State | B5: FCS-Universe | C5: 9.5 | D5: 175 | E5: -235 | F5: =IF(D5>0,100/(D5+100),-D5/(-D5+100)) -> 0.36363636 | G5: =IF(E5>0,100/(E5+100),-E5/(-E5+100)) -> 0.70149254 | H5: =F5/(F5+G5) -> 0.34140127 | I5: =C5+Parameters!$B$6*NORMSINV(H5) -> 8.600988 | J5: 30 | K5: 46.67 | L5: 0.5254 | M5: 10 | N5: =Parameters!$B$2*I5 -> 43.00494 | O5: =Parameters!$B$4*((Parameters!$B$9-M5)*L5+M5) -> 27.627 | P5: =N5+O5 -> 70.63194 | Q5: =(O5-Parameters!$B$4*M5)/P5 -> 0.037192805 | R5: =IF(Parameters!$B$4*M5/P5>Parameters!$B$18,0,Parameters!$B$16+(Parameters!$B$17-Parameters!$B$16)*(Q5-MIN(Q$2:Q$139))/(MAX(Q$2:Q$139)-MIN(Q$2:Q$139))) -> 0 | S5: =ROUND(P5*(1-R5)/Parameters!$B$10,0)*Parameters!$B$10 -> 70.63
A6: Ohio State | B6: Big Ten | C6: 9.5 | D6: -185 | E6: 140 | F6: =IF(D6>0,100/(D6+100),-D6/(-D6+100)) -> 0.64912281 | G6: =IF(E6>0,100/(E6+100),-E6/(-E6+100)) -> 0.41666667 | H6: =F6/(F6+G6) -> 0.6090535 | I6: =C6+Parameters!$B$6*NORMSINV(H6) -> 10.109077 | J6: 100 | K6: 93.7 | L6: 0.6329 | M6: 1 | N6: =Parameters!$B$2*I6 -> 50.545383 | O6: =Parameters!$B$4*((Parameters!$B$9-M6)*L6+M6) -> 19.90475 | P6: =N6+O6 -> 70.450133 | Q6: =(O6-Parameters!$B$4*M6)/P6 -> 0.24705063 | R6: =IF(Parameters!$B$4*M6/P6>Parameters!$B$18,0,Parameters!$B$16+(Parameters!$B$17-Parameters!$B$16)*(Q6-MIN(Q$2:Q$139))/(MAX(Q$2:Q$139)-MIN(Q$2:Q$139))) -> 0.021321039 | S6: =ROUND(P6*(1-R6)/Parameters!$B$10,0)*Parameters!$B$10 -> 68.95
A7: Georgia | B7: SEC | C7: 9.5 | D7: -200 | E7: 154 | F7: =IF(D7>0,100/(D7+100),-D7/(-D7+100)) -> 0.66666667 | G7: =IF(E7>0,100/(E7+100),-E7/(-E7+100)) -> 0.39370079 | H7: =F7/(F7+G7) -> 0.62871287 | I7: =C7+Parameters!$B$6*NORMSINV(H7) -> 10.222582 | J7: 95 | K7: 91.08 | L7: 0.603 | M7: 1 | N7: =Parameters!$B$2*I7 -> 51.112909 | O7: =Parameters!$B$4*((Parameters!$B$9-M7)*L7+M7) -> 19.0825 | P7: =N7+O7 -> 70.195409 | Q7: =(O7-Parameters!$B$4*M7)/P7 -> 0.2362334 | R7: =IF(Parameters!$B$4*M7/P7>Parameters!$B$18,0,Parameters!$B$16+(Parameters!$B$17-Parameters!$B$16)*(Q7-MIN(Q$2:Q$139))/(MAX(Q$2:Q$139)-MIN(Q$2:Q$139))) -> 0.020737489 | S7: =ROUND(P7*(1-R7)/Parameters!$B$10,0)*Parameters!$B$10 -> 68.74
A8: Oregon | B8: Big Ten | C8: 10.5 | D8: 110 | E8: -145 | F8: =IF(D8>0,100/(D8+100),-D8/(-D8+100)) -> 0.47619048 | G8: =IF(E8>0,100/(E8+100),-E8/(-E8+100)) -> 0.59183673 | H8: =F8/(F8+G8) -> 0.44585987 | I8: =C8+Parameters!$B$6*NORMSINV(H8) -> 10.200517 | J8: 81 | K8: 82.6 | L8: 0.6025 | M8: 1 | N8: =Parameters!$B$2*I8 -> 51.002587 | O8: =Parameters!$B$4*((Parameters!$B$9-M8)*L8+M8) -> 19.06875 | P8: =N8+O8 -> 70.071337 | Q8: =(O8-Parameters!$B$4*M8)/P8 -> 0.23645546 | R8: =IF(Parameters!$B$4*M8/P8>Parameters!$B$18,0,Parameters!$B$16+(Parameters!$B$17-Parameters!$B$16)*(Q8-MIN(Q$2:Q$139))/(MAX(Q$2:Q$139)-MIN(Q$2:Q$139))) -> 0.020749469 | S8: =ROUND(P8*(1-R8)/Parameters!$B$10,0)*Parameters!$B$10 -> 68.62
A9: Indiana | B9: Big Ten | C9: 10.5 | D9: -105 | E9: -120 | F9: =IF(D9>0,100/(D9+100),-D9/(-D9+100)) -> 0.51219512 | G9: =IF(E9>0,100/(E9+100),-E9/(-E9+100)) -> 0.54545455 | H9: =F9/(F9+G9) -> 0.48427673 | I9: =C9+Parameters!$B$6*NORMSINV(H9) -> 10.41327 | J9: 52 | K9: 65.91 | L9: 0.5461 | M9: 1 | N9: =Parameters!$B$2*I9 -> 52.066351 | O9: =Parameters!$B$4*((Parameters!$B$9-M9)*L9+M9) -> 17.51775 | P9: =N9+O9 -> 69.584101 | Q9: =(O9-Parameters!$B$4*M9)/P9 -> 0.21582157 | R9: =IF(Parameters!$B$4*M9/P9>Parameters!$B$18,0,Parameters!$B$16+(Parameters!$B$17-Parameters!$B$16)*(Q9-MIN(Q$2:Q$139))/(MAX(Q$2:Q$139)-MIN(Q$2:Q$139))) -> 0.019636348 | S9: =ROUND(P9*(1-R9)/Parameters!$B$10,0)*Parameters!$B$10 -> 68.22
A10: Texas | B10: SEC | C10: 9.5 | D10: 105 | E10: -135 | F10: =IF(D10>0,100/(D10+100),-D10/(-D10+100)) -> 0.48780488 | G10: =IF(E10>0,100/(E10+100),-E10/(-E10+100)) -> 0.57446809 | H10: =F10/(F10+G10) -> 0.4592086 | I10: =C10+Parameters!$B$6*NORMSINV(H10) -> 9.2746591 | J10: 95 | K10: 87.92 | L10: 0.5943 | M10: 1 | N10: =Parameters!$B$2*I10 -> 46.373295 | O10: =Parameters!$B$4*((Parameters!$B$9-M10)*L10+M10) -> 18.84325 | P10: =N10+O10 -> 65.216545 | Q10: =(O10-Parameters!$B$4*M10)/P10 -> 0.25059975 | R10: =IF(Parameters!$B$4*M10/P10>Parameters!$B$18,0,Parameters!$B$16+(Parameters!$B$17-Parameters!$B$16)*(Q10-MIN(Q$2:Q$139))/(MAX(Q$2:Q$139)-MIN(Q$2:Q$139))) -> 0.0215125 | S10: =ROUND(P10*(1-R10)/Parameters!$B$10,0)*Parameters!$B$10 -> 63.81
A11: Penn State | B11: Big Ten | C11: 8.5 | D11: -165 | E11: 130 | F11: =IF(D11>0,100/(D11+100),-D11/(-D11+100)) -> 0.62264151 | G11: =IF(E11>0,100/(E11+100),-E11/(-E11+100)) -> 0.43478261 | H11: =F11/(F11+G11) -> 0.58882855 | I11: =C11+Parameters!$B$6*NORMSINV(H11) -> 8.9939717 | J11: 85 | K11: 80.98 | L11: 0.5976 | M11: 1 | N11: =Parameters!$B$2*I11 -> 44.969859 | O11: =Parameters!$B$4*((Parameters!$B$9-M11)*L11+M11) -> 18.934 | P11: =N11+O11 -> 63.903859 | Q11: =(O11-Parameters!$B$4*M11)/P11 -> 0.25716757 | R11: =IF(Parameters!$B$4*M11/P11>Parameters!$B$18,0,Parameters!$B$16+(Parameters!$B$17-Parameters!$B$16)*(Q11-MIN(Q$2:Q$139))/(MAX(Q$2:Q$139)-MIN(Q$2:Q$139))) -> 0.021866809 | S11: =ROUND(P11*(1-R11)/Parameters!$B$10,0)*Parameters!$B$10 -> 62.51
A12: BYU | B12: Big 12 | C12: 8.5 | D12: -150 | E12: 115 | F12: =IF(D12>0,100/(D12+100),-D12/(-D12+100)) -> 0.6 | G12: =IF(E12>0,100/(E12+100),-E12/(-E12+100)) -> 0.46511628 | H12: =F12/(F12+G12) -> 0.56331878 | I12: =C12+Parameters!$B$6*NORMSINV(H12) -> 8.8506557 | J12: 56 | K12: 63.1 | L12: 0.5629 | M12: 1 | N12: =Parameters!$B$2*I12 -> 44.253278 | O12: =Parameters!$B$4*((Parameters!$B$9-M12)*L12+M12) -> 17.97975 | P12: =N12+O12 -> 62.233028 | Q12: =(O12-Parameters!$B$4*M12)/P12 -> 0.2487385 | R12: =IF(Parameters!$B$4*M12/P12>Parameters!$B$18,0,Parameters!$B$16+(Parameters!$B$17-Parameters!$B$16)*(Q12-MIN(Q$2:Q$139))/(MAX(Q$2:Q$139)-MIN(Q$2:Q$139))) -> 0.021412092 | S12: =ROUND(P12*(1-R12)/Parameters!$B$10,0)*Parameters!$B$10 -> 60.9
A13: Alabama | B13: SEC | C13: 8.5 | D13: -120 | E13: -105 | F13: =IF(D13>0,100/(D13+100),-D13/(-D13+100)) -> 0.54545455 | G13: =IF(E13>0,100/(E13+100),-E13/(-E13+100)) -> 0.51219512 | H13: =F13/(F13+G13) -> 0.51572327 | I13: =C13+Parameters!$B$6*NORMSINV(H13) -> 8.5867297 | J13: 100 | K13: 88.62 | L13: 0.5963 | M13: 1 | N13: =Parameters!$B$2*I13 -> 42.933649 | O13: =Parameters!$B$4*((Parameters!$B$9-M13)*L13+M13) -> 18.89825 | P13: =N13+O13 -> 61.831899 | Q13: =(O13-Parameters!$B$4*M13)/P13 -> 0.26520696 | R13: =IF(Parameters!$B$4*M13/P13>Parameters!$B$18,0,Parameters!$B$16+(Parameters!$B$17-Parameters!$B$16)*(Q13-MIN(Q$2:Q$139))/(MAX(Q$2:Q$139)-MIN(Q$2:Q$139))) -> 0.022300504 | S13: =ROUND(P13*(1-R13)/Parameters!$B$10,0)*Parameters!$B$10 -> 60.45
... A139: Charlotte | B139: AAC | C139: 2.5 | D139: 120 | E139: -155 | F139: =IF(D139>0,100/(D139+100),-D139/(-D139+100)) -> 0.45454545 | G139: =IF(E139>0,100/(E139+100),-E139/(-E139+100)) -> 0.60784314 | H139: =F139/(F139+G139) -> 0.42785235 | I139: =C139+Parameters!$B$6*NORMSINV(H139) -> 2.0999419 | J139: 18 | K139: 17.8 | L139: 0.3257 | M139: 1 | N139: =Parameters!$B$2*I139 -> 10.49971 | O139: =Parameters!$B$4*((Parameters!$B$9-M139)*L139+M139) -> 11.45675 | P139: =N139+O139 -> 21.95646 | Q139: =(O139-Parameters!$B$4*M139)/P139 -> 0.40793234 | R139: =IF(Parameters!$B$4*M139/P139>Parameters!$B$18,0,Parameters!$B$16+(Parameters!$B$17-Parameters!$B$16)*(Q139-MIN(Q$2:Q$139))/(MAX(Q$2:Q$139)-MIN(Q$2:Q$139))) -> 0.03 | S139: =ROUND(P139*(1-R139)/Parameters!$B$10,0)*Parameters!$B$10 -> 21.3
A141: Blue cells = inputs (odds, brand/popularity/capture from engine.py). Black = live formulas driven by the Parameters tab.

Sheet Methodology
A1: InPlay Football Trading Challenge — IPO Pricing System v1.0
A3: IPO price = expected terminal (liquidating) distribution per share:
A4: IPO = $5.00 x E[Wins] + $2.50 x E[Ties] (NFL only) + $2.50/game x E[Volume Capture Share]
A5: Per SDMM-1 retained-earnings accrual and Consolidated Novosapien Spec v1.1-v1.3: off-field pool splits
A6: pro rata by counted share volume, capture clamped to [0.20, 0.80]; games vs non-universe opponents pay
A7: the universe team the full $2.50; regular season only.
A9: ON-FIELD: BetMGM season win-total prices are devigged proportionally to P(over). Season wins are modeled
A10: Normal(mu, sigma) around the posted line; mu = line + sigma * InvNorm(P_over). Sigma is the market-implied
A11: dispersion of season wins (NFL 2.7, NCAA 2.2 — Parameters tab).
A13: OFF-FIELD (Popularity Index at IPO): Pop = 0.6 x Brand + 0.4 x PerfIndex, where Brand is a hand-assigned
A14: 0-100 fanbase/brand tier (Base Demand Index proxy — no realized volume exists at IPO) and PerfIndex =
A15: 100 x E[Wins]/Games (traders gravitate to winners). Expected per-game capture vs opponent j is Bradley-Terry:
... A34: = 12 x $5 + 12 x $2.00 = $84.00. All IPOs price well inside their ceilings.
